[
{"titulo": ["Songs for a Hero - Definitive Edition"], "preco": ["R$ 22,49"], "preco_sem_desconto": ["R$ 29,99"], "desconto": ["-25%"]},
{"titulo": ["Red Dead Redemption 2"], "preco": ["R$ 119,50", "R$ 139,96"], "preco_sem_desconto": ["R$ 239,00", "R$ 349,90"], "desconto": ["-50%", "-60%"]},
{"titulo": ["LEGO® Builder's Journey"], "preco": ["R$ 25,45"], "preco_sem_desconto": ["R$ 37,99"], "desconto": ["-33%"]},
{"titulo": ["My Time At Portia"], "preco": ["R$ 19,97"], "preco_sem_desconto": ["R$ 79,90"], "desconto": ["-75%"]},
{"titulo": ["Farming Simulator 22"], "preco": "R$ 159,00", "preco_sem_desconto": "0", "desconto": "0"},
{"titulo": ["Among Us"], "preco": ["R$ 8,16"], "preco_sem_desconto": ["R$ 10,89"], "desconto": ["-25%"]},
{"titulo": ["DEATH STRANDING"], "preco": ["R$ 71,70"], "preco_sem_desconto": ["R$ 239,00"], "desconto": ["-70%"]},
{"titulo": ["while True: learn()"], "preco": ["R$ 18,55", "R$ 68,92", "R$ 42,43", "R$ 21,65"], "preco_sem_desconto": ["R$ 26,89", "R$ 100,53", "R$ 60,56", "R$ 33,38"], "desconto": ["-31%", "-31%", "-30%", "-35%"]},
{"titulo": ["LEGO® Batman™: The Videogame"], "preco": ["R$ 9,24", "R$ 18,19"], "preco_sem_desconto": ["R$ 36,99", "R$ 90,99"], "desconto": ["-75%", "-80%"]},
{"titulo": ["Mafia II: Definitive Edition"], "preco": ["R$ 56,09", "R$ 139,95"], "preco_sem_desconto": ["R$ 169,99", "R$ 279,90"], "desconto": ["-67%", "-50%"]},
{"titulo": ["Overcooked"], "preco": ["R$ 7,79", "R$ 32,06", "R$ 33,15", "R$ 10,90"], "preco_sem_desconto": ["R$ 38,99", "R$ 158,79", "R$ 151,95", "R$ 49,48"], "desconto": ["-80%", "-80%", "-78%", "-78%"]},
{"titulo": ["LEGO® Batman™ 2: DC Super Heroes"], "preco": ["R$ 9,24", "R$ 18,19"], "preco_sem_desconto": ["R$ 36,99", "R$ 90,99"], "desconto": ["-75%", "-80%"]},
{"titulo": ["Never Alone (Kisima Ingitchuna)"], "preco": ["R$ 5,99", "R$ 7,19", "R$ 32,91"], "preco_sem_desconto": ["R$ 29,99", "R$ 35,99", "R$ 75,97"], "desconto": ["-80%", "-80%", "-57%"]},
{"titulo": ["PC Building Simulator"], "preco": ["R$ 15,19", "R$ 99,02", "R$ 32,47", "R$ 24,99"], "preco_sem_desconto": ["R$ 37,99", "R$ 162,50", "R$ 75,98", "R$ 48,88"], "desconto": ["-60%", "-39%", "-57%", "-49%"]},
{"titulo": ["Eastward"], "preco": ["R$ 43,19", "R$ 150,98"], "preco_sem_desconto": ["R$ 47,99", "R$ 271,92"], "desconto": ["-10%", "-44%"]},
{"titulo": ["Overcooked! 2"], "preco": ["R$ 14,97", "R$ 35,63", "R$ 32,06", "R$ 47,65"], "preco_sem_desconto": ["R$ 59,90", "R$ 116,77", "R$ 158,79", "R$ 135,88"], "desconto": ["-75%", "-69%", "-80%", "-65%"]},
{"titulo": ["Vampyr"], "preco": ["R$ 37,47"], "preco_sem_desconto": ["R$ 149,90"], "desconto": ["-75%"]},
{"titulo": ["LEGO® Batman™ 3: Beyond Gotham"], "preco": ["R$ 11,99", "R$ 18,19", "R$ 19,97", "R$ 29,99", "R$ 52,49"], "preco_sem_desconto": ["R$ 79,99", "R$ 90,99", "R$ 79,90", "R$ 199,99", "R$ 349,99"], "desconto": ["-85%", "-80%", "-75%", "-85%", "-85%"]},
{"titulo": ["Enter the Gungeon"], "preco": ["R$ 13,99", "R$ 23,76", "R$ 21,85"], "preco_sem_desconto": ["R$ 27,99", "R$ 48,68", "R$ 48,46"], "desconto": ["-50%", "-51%", "-55%"]},
{"titulo": ["Darkest Dungeon®"], "preco": ["R$ 6,89", "R$ 23,11", "R$ 35,24"], "preco_sem_desconto": ["R$ 45,99", "R$ 105,55", "R$ 218,95"], "desconto": ["-85%", "-78%", "-84%"]},
{"titulo": ["Minit"], "preco": ["R$ 7,99", "R$ 63,43", "R$ 47,17"], "preco_sem_desconto": ["R$ 19,99", "R$ 134,84", "R$ 114,55"], "desconto": ["-60%", "-53%", "-59%"]},
{"titulo": ["South Park™: The Stick of Truth™"], "preco": ["R$ 22,49", "R$ 53,98"], "preco_sem_desconto": ["R$ 89,99", "R$ 239,98"], "desconto": ["-75%", "-78%"]},
{"titulo": ["A Plague Tale: Innocence"], "preco": ["R$ 32,47"], "preco_sem_desconto": ["R$ 129,90"], "desconto": ["-75%"]},
{"titulo": ["Far Cry 3"], "preco": ["R$ 17,99", "R$ 26,99", "R$ 69,99", "R$ 148,42"], "preco_sem_desconto": ["R$ 59,99", "R$ 89,99", "R$ 349,99", "R$ 644,92"], "desconto": ["-70%", "-70%", "-80%", "-77%"]},
{"titulo": ["Far Cry®"], "preco": ["R$ 8,99", "R$ 148,42"], "preco_sem_desconto": ["R$ 29,99", "R$ 644,92"], "desconto": ["-70%", "-77%"]},
{"titulo": ["Far Cry® 4"], "preco": ["R$ 26,99", "R$ 44,99", "R$ 148,42"], "preco_sem_desconto": ["R$ 89,99", "R$ 179,99", "R$ 644,92"], "desconto": ["-70%", "-75%", "-77%"]},
{"titulo": ["SUPERHOT"], "preco": ["R$ 15,99", "R$ 27,18", "R$ 46,47", "R$ 32,18"], "preco_sem_desconto": ["R$ 39,99", "R$ 79,98", "R$ 129,97", "R$ 89,98"], "desconto": ["-60%", "-66%", "-64%", "-64%"]},
{"titulo": ["Far Cry® 5"], "preco": ["R$ 35,99", "R$ 51,99", "R$ 59,99", "R$ 69,99", "R$ 148,42"], "preco_sem_desconto": ["R$ 179,99", "R$ 259,99", "R$ 299,99", "R$ 349,99", "R$ 644,92"], "desconto": ["-80%", "-80%", "-80%", "-80%", "-77%"]}
]